hermione_databricks/__init__.py
hermione_databricks/version.py
hermione_databricks/api/__init__.py
hermione_databricks/api/project.py
hermione_databricks/api/resources.py
hermione_databricks/api/sync.py
hermione_databricks/cli/__init__.py
hermione_databricks/cli/cli.py
hermione_databricks/databricks_file_text/README.ipynb
hermione_databricks/databricks_file_text/FileSystem/artifacts/.gitkeep
hermione_databricks/databricks_file_text/FileSystem/data/feature/.gitkeep
hermione_databricks/databricks_file_text/FileSystem/data/ml_input/.gitkeep
hermione_databricks/databricks_file_text/FileSystem/data/ml_output/.gitkeep
hermione_databricks/databricks_file_text/FileSystem/data/raw/.gitkeep
hermione_databricks/databricks_file_text/model/model.ipynb
hermione_databricks/databricks_file_text/notebooks/exploratory_analysis.ipynb
hermione_databricks/databricks_file_text/preprocessing/preprocessing.ipynb
hermione_databricks/tests/__init__.py
hermione_databricks/tests/test_api.py
hermione_databricks/tests/test_cli.py
hermione_databricks-1.0.7.dist-info/LICENSE
hermione_databricks-1.0.7.dist-info/METADATA
hermione_databricks-1.0.7.dist-info/WHEEL
hermione_databricks-1.0.7.dist-info/entry_points.txt
hermione_databricks-1.0.7.dist-info/top_level.txt
hermione_databricks-1.0.7.dist-info/RECORD
