Metadata-Version: 2.1
Name: hermione-databricks
Version: 1.0.7
Summary: UNKNOWN
Home-page: https://github.com/igorpereirabr1/hermione_databricks
Author: igor.pereira.br@gmail.com
Author-email: ju195@cummins.com
License: Apache License 2.0
Keywords: machine learning mlops devops artificial intelligence
Platform: UNKNOWN
Classifier: Development Status :: 3 - Alpha
Classifier: License :: OSI Approved :: Apache Software License
Classifier: Programming Language :: Python :: 3.6
Classifier: Programming Language :: Python :: 3.7
Classifier: Programming Language :: Python :: 3.8
Classifier: Topic :: Scientific/Engineering :: Artificial Intelligence
Classifier: Topic :: Software Development
Requires-Python: >=3.6
Requires-Dist: databricks-cli
Requires-Dist: Click
